supsrc/__init__.py
supsrc/_version.py
supsrc/example_helper.py
supsrc/exceptions.py
supsrc/protocols.py
supsrc/rules.py
supsrc/types.py
supsrc/cli/__init__.py
supsrc/cli/config_cmds.py
supsrc/cli/main.py
supsrc/cli/sui_cmds.py
supsrc/cli/utils.py
supsrc/cli/watch_cmds.py
supsrc/config/__init__.py
supsrc/config/defaults.py
supsrc/config/models.py
supsrc/engines/__init__.py
supsrc/engines/git/__init__.py
supsrc/engines/git/auth.py
supsrc/engines/git/base.py
supsrc/engines/git/events.py
supsrc/engines/git/info.py
supsrc/engines/git/operations.py
supsrc/events/__init__.py
supsrc/events/base.py
supsrc/events/buffer_events.py
supsrc/events/collector.py
supsrc/events/defaults.py
supsrc/events/feed.py
supsrc/events/feed_table.py
supsrc/events/json_logger.py
supsrc/events/monitor.py
supsrc/events/processor.py
supsrc/events/protocol.py
supsrc/events/system.py
supsrc/events/timer.py
supsrc/events/buffer/__init__.py
supsrc/events/buffer/converters.py
supsrc/events/buffer/core.py
supsrc/events/buffer/grouping.py
supsrc/events/buffer/streaming.py
supsrc/events/feed_table/__init__.py
supsrc/events/feed_table/file_utils.py
supsrc/events/feed_table/formatters.py
supsrc/events/feed_table/widget.py
supsrc/events/src/supsrc/utils/__init__.py
supsrc/llm/__init__.py
supsrc/llm/prompts.py
supsrc/llm/providers/__init__.py
supsrc/llm/providers/base.py
supsrc/llm/providers/gemini.py
supsrc/llm/providers/ollama.py
supsrc/monitor/__init__.py
supsrc/monitor/events.py
supsrc/monitor/handler.py
supsrc/monitor/service.py
supsrc/output/__init__.py
supsrc/output/console_formatter.py
supsrc/output/emoji_map.py
supsrc/output/verbose_formats/__init__.py
supsrc/output/verbose_formats/base.py
supsrc/output/verbose_formats/compact.py
supsrc/output/verbose_formats/table.py
supsrc/runtime/__init__.py
supsrc/runtime/action_handler.py
supsrc/runtime/monitoring_coordinator.py
supsrc/runtime/orchestrator.py
supsrc/runtime/repository_manager.py
supsrc/runtime/status_manager.py
supsrc/runtime/tui_interface.py
supsrc-0.2.0.dist-info/licenses/LICENSE
supsrc-0.2.0.dist-info/METADATA
supsrc-0.2.0.dist-info/WHEEL
supsrc-0.2.0.dist-info/entry_points.txt
supsrc-0.2.0.dist-info/top_level.txt
supsrc-0.2.0.dist-info/RECORD
