Metadata-Version: 2.4
Name: supsrc
Version: 0.2.0
Summary: Automated Git commit/push utility based on filesystem events and rules.
Author-email: Tim Perkins <code@tim.life>
Maintainer-email: "provide.io" <code@provide.io>
License-Expression: Apache-2.0
Project-URL: Homepage, https://github.com/provide-io/supsrc
Project-URL: Repository, https://github.com/provide-io/supsrc
Project-URL: Issues, https://github.com/provide-io/supsrc/issues
Keywords: git,automation,watchdog,developer-tools,vcs,backup,llm
Classifier: Development Status :: 3 - Alpha
Classifier: Environment :: Console
Classifier: Environment :: Console :: Curses
Classifier: Intended Audience :: Developers
Classifier: Operating System :: MacOS :: MacOS X
Classifier: Operating System :: POSIX :: Linux
Classifier: Programming Language :: Python :: 3
Classifier: Programming Language :: Python :: 3.11
Classifier: Programming Language :: Python :: 3.12
Classifier: Programming Language :: Python :: 3.13
Classifier: Topic :: Software Development :: Version Control
Classifier: Topic :: System :: Filesystems
Classifier: Topic :: Utilities
Classifier: Typing :: Typed
Requires-Python: >=3.11
License-File: LICENSE
Requires-Dist: provide-foundation[all]>=0.0.0.dev3
Requires-Dist: cattrs>=24.1.3
Requires-Dist: pygit2>=1.18.0
Requires-Dist: watchdog>=6.0.0
Requires-Dist: pathspec>=0.12.1
Requires-Dist: sshconf>=0.2.7
Requires-Dist: rich>=13.7.1
Requires-Dist: aioconsole>=0.8.1
Requires-Dist: packaging>=24.0
Provides-Extra: tui
Requires-Dist: textual>=0.70.0; extra == "tui"
Provides-Extra: llm
Requires-Dist: google-genai>=0.5.0; extra == "llm"
Requires-Dist: ollama>=0.2.0; extra == "llm"
Dynamic: license-file
